{
  "common": {
    "logo_text": "Connecteurs pour palplanches en acier",
    "login": "Login",
    "logout": "Se déconnecter",
    "menu": "Menu",
    "email": "E-mail",
    "password": "Mot de passe",
    "register": "Enregistrement",
    "related_section": "Section connexe",
    "copyright": "Copyright",
    "home": "Maison",
    "fax": "Fax",
    "phone": "Téléphone",
    "confirm": "confirmer",
    "cancel": "Annuler"
  },

  "alert": {
    "are_you_sure": "Es-tu sûr"
  },

  "home_nav": {
    "connectors": "Connecteurs",
    "downloads": "Téléchargements",
    "gallery": "Galerie",
    "sealant": "Produit d’étanchéité",
    "contact": "Contact",
    "user_information": "Informations utilisateur",
    "about_steelwall": "À propos de Steelwall",
    "newsletter": "Bulletin",
    "languages_and_measures": "Langues et unités de mesure",
    "legal_advice": "Mentions légales",
    "imprint": "Mentions légales",
    "privacy_policy": "Politique de confidentialité",
    "general_terms_and_conditions": "Conditions générales",
    "favourites": "Favoris",
    "profile": "Profil"
  },


  "home_footer": {
    "disclaimer": "Notes techniques / clause de non-responsabilité",
    "disclaimer_text": "Les profilés SteelWall répondent de manière générale aux normes européennes et sont fabriqués dans des entreprises certifiées de l’industrie sidérurgique. Toutes les indications chiff-rées sont des valeurs approximatives et sont susceptibles de varier. Des torsions de barre de jusqu’à 2 mm par mètre sont possibles. Tolérance de l’épaisseur d’acier : ±1 mm. L’épaisseur de\nl’acier peut être réduite de jusqu’à 2 mm aux extrémités des profilés. Tolérance de longueur : jusqu’à ±200 mm. Les indications de degrés se réfèrent aux axes des connecteurs. Sous réserve de modifications techniques. Nous nous référons à la norme DIN EN 12063. Veuillez vérifier la compatibilité des lisières de serrures de palplanches à l’aide de sections de spécimens des\nconnecteurs souhaités.",
    "last_website_update": "Dernière mise à jour du site Web :",
    "africa": "Afrique",
    "asia": "Asie",
    "australia": "Australie",
    "caribbean": "Caraïbes",
    "europe": "Europe",
    "india": "Inde",
    "new_zealand": "Nouvelle-Zélande",
    "south_america": "Amérique du Sud",
    "north_america": "Amérique du Nord",
    "south_east_asia": "Asie du Sud-Est",
    "japan": "Japan",
    "oceania": "Océanie",
    "about_mf_pipe": "MF-Pipe est une division\nde SteelWall-ISH GmbH"
  },


  "login_page": {
    "forgot_password": "Mot de passe oublié",
    "not_a_member": "Pas un membre?"
  },

  "user_info": {
    "your_name": "Votre nom",
    "job_position": "Emploi / Poste",
    "division": "Division",
    "company_name": "Nom de l'entreprise",
    "country_state": "Pays / État",
    "website": "Site web",
    "phone": "Téléphone",
    "email": "E-mail"
  },


  "register_page": {
    "advantages_of_a_registration": "Avantages d'une inscription",
    "request_products_easily": "Demandez des produits facilement !",
    "save_your_requests_and_products": "Sauvegardez vos demandes et produits (Favoris) !",
    "receive_latest_connector_information_via_newsletter": "Recevez les dernières informations sur les connecteurs via la newsletter !",
    "subscribe_to_newsletter": "S'inscrire à la Newsletter",
    "by_subscribing_you_will_automatically_receive_our_newsletter": "En vous inscrivant, vous recevrez automatiquement notre newsletter",
    "already_a_member": "Déjà membre?"
  },


  "download_page": {
    "downloads": "Téléchargements",
    "please_register_before_download": "Veuillez vous inscrire avant de télécharger!",
    "test_reports": "Rapports d'essai",
    "test_report": "Rapport d'essai",
    "brochures": "Brochures",
    "data_sheets": "Fiche technique",
    "brochures_and_data_sheets": "Brochures et fiches techniques",
    "steelwall_connectors_overview": "Steelwall aperçu des connecteurs"
  },


  "gallery_page": {
    "gallery": "Galerie"
  },

  "contact_page": {
    "contact": "Contact",
    "headquarters_germany": "SIEGE ALLEMAGNE",
    "sales_line_north_america": "LIGNE DE VENTE AMÉRIQUE DU NORD",
    "headquarters": "Quartier général",
    "please_leave_a_message_here": "Veuillez laisser un message ici",
    "send": "Envoyer",
    "your_message": "VOTRE MESSAGE"
  },

  "profile_page": {
    "update": "Mise à jour",
    "profile": "Profil",
    "old_password": "ancien mot de passe",
    "new_password": "nouveau mot de passe",
    "verify_password": "vérifier le mot de passe"
  },


  "favourites_page": {
    "favourites": "Favoris",
    "your_request": "Votre demande",
    "favourite_connectors": "Connecteurs favoris",
    "project_name": "Titre du projet",
    "connector_name": "Nom du connecteur",
    "date_time_of_request": "Date/Heure de la demande",
    "amount": "Montant (running m)",
    "location": "Emplacement",
    "country_state": "Pays / État",
    "seen_on_date_or_time": "Vu le date/heure",
    "status": "Statut",
    "delete_message": "Si vous continuez à supprimer"
  },


  "template_context": {
    "steel_grade": "Nuance d‘acier",
    "steel_thickness": "Épaisseur de l’acier",
    "standard_length": "Longueur standard",
    "standard_lengths": "longueurs standard",
    "standard_length_variable": "Longueurs standard sur demande, variables de",
    "max_tensile_strength": "Force de traction max",
    "weight": "Poids",
    "request_this_connector": "Faire une demande pour un profilé",
    "remember_this_connector": "Mémoriser profilé",
    "pressure_load": "Pressure load",
    "deformation_path": "Deformation path",
    "length": "longueur"
  },

  "connector_mf_64": {
    "test_setup": "Configuration des tests",
    "after_testing": "Après essai, rupture par déformation",
    "conclusion": "Conclusion"
  },

  "connector_page": {
    "add_to_favourite_message": "Vous souhaitez ajouter ce connecteur en favori",
    "connector_series": "SÉRIE DE CONNECTEUR"
  },

  "about_page": {
    "about_steel_wall": "À propos de SteelWall",
    "more_than_25_years_of_experience_in_creating_connectors_for_steel_walls": "De nombreuses années d’expérience dans le développement de connecteurs pour rideaux de palplanches en acier",
    "paragraph_01": "SteelWall ISH s’occupe du développement, de la production et de la vente de systèmes de\nserrures en acier pour l’assemblage de tubes en acier (palplanches tubulaires), de poutres en\nacier (palplanches en H) et de tôles en acier avec des lisières de serrure (palplanches) afin de\nréaliser des murs de soutènement et de retenue en acier continus, reliés entre eux et très\nsolides, appelés rideaux de palplanches en acier.",
    "paragraph_02": "Les rideaux de palplanches en acier sont utilisés depuis plus de 100 ans dans les ouvrages\nsuivants : fouilles, ponts, sauts de terrain, murs de quai, bassins portuaires, murs d’écluse,\ncanaux, jetées, pour la protection contre les crues, la construction de tunnels, de parkings\nsouterrains et pour l’encapsulage de sites contaminés.",
    "paragraph_03": "Fabriqués dans des entreprises certifi ées de transformation de l’acier, les systèmes de connecteurs en acier SteelWall de troisième génération sont techniquement parfaits, extrêmement stables, faciles à foncer et, en même temps, d’une rentabilité imbattable.",
    "paragraph_04": ""
  },
  "news_letter_page": {
    "newsletter": "Bulletin",
    "subscribe_unsubscribe": "S'inscrire Se désinscrire",
    "advantages_of_a_registration": "Avantages d'une inscription",
    "request_products_easily": "Demandez des produits facilement",
    "save_your_requests_and_products": "Sauvegardez vos demandes et produits",
    "receive_latest_connector_information_via_newsletter": "Recevez les dernières informations sur les connecteurs via la newsletter (environ 4 fois / an)",
    "unsubscribe": "Se désabonner",
    "Subscribe": "S'abonner",
    "login_to_subscribe": "Connectez-vous pour vous abonner"
  },
  "imprint": {
    "legal_advices": "Mentions légales",
    "publisher": "Éditeur :<br/><br/>",
    "publisher_detail": "SteelWall ISH GmbH<br/>Tassilostr. 21<br/>82166 Gräfelfing<br/>Allemagne<br/>",
    "managing_partner": "Représentant habilité :",
    "mp_name": "Richard Heindl",
    "mp_contact": "Tél. : +49-89-74 120 122<br/>Fax : +49-89-74 120 128<br/>E-mail : info@steelwall.eu",
    "register_court": "Tribunal chargé de la tenue du registre :",
    "registration_detail": "Inscrit au registre du commerce<br/>Tribunal chargé de la tenue du registre : Tribunal administratif de Munich<br/>Numéro d’enregistrement : HRB89130<br/>N° de TVA : DE129389226",
    "legal_notice": "Mentions légales :",
    "legal_detail": "Le contenu de ce site Web est protégé par le droit d’auteur. Une copie des informations sur\nle site Web peut être stockée sur un seul ordinateur pour un usage interne, non commercial\net personnel. Les graphiques, textes, logos, images, etc. ne peuvent être téléchargés, reproduits, copiés, modifiés, publiés, envoyés, transmis ou utilisés sous quelque forme que ce\nsoit qu’avec l’accord écrit de SteelWall ISH GmbH. Les fichiers DWG mis à disposition pour\ntéléchargement ne peuvent pas être modifiés, redistribués ou mis à la disposition du public.\nLes noms de produits et de sociétés mentionnés peuvent être des marques déposées ou des\nmarques. L’utilisati on non autorisée peut donner lieu à des demandes de dommages et intérêts et à des demandes d’injonction.",
    "design": "Conception et design :<br/>Werbeagentur Armin Meier, Passau, <a href='https://www.meier-design.com/'  target='_blank' style='text-decoration: none;'>www.meier-design.com</a>",
    "programming": "Programmierung :<br/><a href='https://comalpine-infosys.de/'   target='_blank' style='text-decoration: none;'>comAlpine Informationssysteme GmbH, Passau (Allemagne)</a>"
  },
  "privacy": {
    "privacy_policy": "Datenschutzerklärung",
    "legal_advices" : "Rechtliche Hinweise",
    "contact_details": "Kontaktdaten",
    "controller": "Verantwortlicher",
    "controller_detail": "Richard Heindl, Email: info@steelwall.eu, Telephone: 49-89-74 120 122",
    "purposes": "Zwecke",
    "purpose_detail": "Sicherstellung eines problemlosen Zugriffs auf unsere Internetseite, Auswertung der Systemstabilität, Systemsicherheit, Nutzungskomfort der Internetseite, Vorbestellungen, administrative Zwecke bzgl. Interseite; Keinesfalls werden Daten erhoben, um Rückschlüsse auf Personen zu ziehen.",
    "legal_basis": "Rechtsgrundlage:",
    "newsletter": "Newsletter",
    "cookies": "Cookies"
  },
  "terms_and_conditions": {
    "general_terms_and_conditions": "Conditions générales",
    "legal_advices" : "Mentions légales",
    "please_download_open_pdf_file": "Veuillez télécharger/ouvrir le fichier PDF"
  },














  "sideBar": {
    "dashboard": "Dashboardddddddd",
    "incidents": "Incidents",
    "property": "Property",
    "properties": "Properties",
    "flats": "Flats",
    "maintenance": "Maintenance",
    "maintenanceMans": "Maintenance Mans",
    "deputies": "Deputies",
    "management": "Management",
    "tenant_and_owner": "Tenants & Owners",
    "tenants": "Tenants",
    "owners": "Owners",
    "utility": "Utility",
    "calendar": "Calendar"
  },
  "dashboard": {
    "heading": "Dashboarddddddddd"
  }
}